uiautodev/__init__.py
uiautodev/__main__.py
uiautodev/app.py
uiautodev/appium_proxy.py
uiautodev/binaries/scrcpy-server-v2.7.jar
uiautodev/binaries/scrcpy-server-v3.3.3.jar
uiautodev/case.py
uiautodev/cli.py
uiautodev/command_proxy.py
uiautodev/command_types.py
uiautodev/common.py
uiautodev/driver/android/__init__.py
uiautodev/driver/android/adb_driver.py
uiautodev/driver/android/common.py
uiautodev/driver/android/u2_driver.py
uiautodev/driver/appium.py
uiautodev/driver/base_driver.py
uiautodev/driver/harmony.py
uiautodev/driver/ios.py
uiautodev/driver/mock.py
uiautodev/driver/testdata/layout.json
uiautodev/driver/udt/appium-uiautomator2-v5.12.4-light.apk
uiautodev/driver/udt/udt.py
uiautodev/exceptions.py
uiautodev/model.py
uiautodev/provider.py
uiautodev/remote/android_input.py
uiautodev/remote/harmony_mjpeg.py
uiautodev/remote/keycode.py
uiautodev/remote/scrcpy.py
uiautodev/remote/touch_controller.py
uiautodev/router/android.py
uiautodev/router/device.py
uiautodev/router/proxy.py
uiautodev/router/xml.py
uiautodev/static/demo.html
uiautodev/utils/common.py
uiautodev/utils/envutils.py
uiautodev/utils/exceptions.py
uiautodev/utils/usbmux.py
uiautodev-0.13.5.dist-info/METADATA
uiautodev-0.13.5.dist-info/WHEEL
uiautodev-0.13.5.dist-info/entry_points.txt
uiautodev-0.13.5.dist-info/licenses/LICENSE
uiautodev-0.13.5.dist-info/RECORD
