Metadata-Version: 2.4
Name: uiautodev
Version: 0.13.5
Summary: Mobile UI Automation, include UI hierarchy inspector, script recorder
License: MIT
License-File: LICENSE
Author: codeskyblue
Author-email: codeskyblue@gmail.com
Requires-Python: >=3.8,<4.0
Classifier: License :: OSI Approved :: MIT License
Classifier: Programming Language :: Python :: 3
Classifier: Programming Language :: Python :: 3.8
Classifier: Programming Language :: Python :: 3.9
Classifier: Programming Language :: Python :: 3.10
Classifier: Programming Language :: Python :: 3.11
Classifier: Programming Language :: Python :: 3.12
Classifier: Programming Language :: Python :: 3.13
Classifier: Programming Language :: Python :: 3.14
Requires-Dist: Pillow (>=9)
Requires-Dist: adbutils (>=2.8.10,<3)
Requires-Dist: click (>=8.1.7,<9.0.0)
Requires-Dist: construct
Requires-Dist: fastapi (>=0.115.12,<1)
Requires-Dist: httpx (>=0.28.1)
Requires-Dist: lxml (>=6.0.2)
Requires-Dist: pydantic (>=2.6,<3.0)
Requires-Dist: pygments (>=2)
Requires-Dist: python-multipart (>=0.0.18)
Requires-Dist: rich
Requires-Dist: uiautomator2 (>=3.2.0,<4)
Requires-Dist: uvicorn (>=0.33.0)
Requires-Dist: wdapy (>0.2.2,<1)
Requires-Dist: websockets (>=10.4)
Project-URL: Homepage, https://uiauto.dev
